[
  {
    "token": "6a367c47-97f0-4b3d-a3db-fe96691d3cb7",
    "title": "Legendary Anime Chronicles",
    "description": "Unraveling the Mysteries of Anime Lore",
    "content": "Deep in the heart of the anime universe lies a treasure trove of untold stories and forgotten legends. From the ancient scrolls of the samurai to the digital archives of futuristic cyberpunk dystopias, the history of anime is as rich and varied as the worlds it portrays. 2. Our journey begins in the distant past, in a time when gods and demons walked the earth and magic was a part of everyday life. It is here that we meet Amaterasu, a young shrine maiden with a gift for wielding powerful elemental magic. Together with her loyal companions, she embarks on a quest to restore balance to a world torn apart by war and strife. 3. As Amaterasu travels across the land, she encounters a host of mythical creatures and legendary heroes, each with their own role to play in the unfolding drama. From the wise old sage who serves as her mentor to the fierce warrior who becomes her sworn enemy, every encounter brings her one step closer to her ultimate destiny. 4. Along the way, Amaterasu discovers long-forgotten relics and ancient artifacts, each holding clues to the mysteries of her past and the fate of her world. From enchanted swords that can cleave mountains in twain to mystical amulets that grant their bearer untold power, every discovery brings her closer to unlocking the secrets of the universe. 5. Yet even as Amaterasu delves deeper into the lore of her world, she also attracts the attention of dark forces that seek to use her powers for their own nefarious ends. From malevolent sorcerers who seek to bend her to their will to ancient demons who hunger for her soul, she must confront enemies more powerful than she ever imagined. 6. But with the help of her friends and allies, Amaterasu refuses to back down from the challenges that lie ahead. For she knows that the fate of the world rests in her hands, and that only by embracing her true power can she hope to overcome the darkness that threatens to consume them all. 7. And so, armed with courage and determination, Amaterasu sets out to write her own legend in the annals of anime history. For in a world where anything is possible, the only limit is the strength of one's imagination..",
    "author": {
      "name": "Kaori Nakamura",
      "email": "kaori.nakamura@example.com"
    },
    "imageURL": "/assets/faces/2.svg",
    "backgroundimg": "/assets/3.jpg",
    "comments": []
  },
  {
    "token": "0ef5ba59-58f6-4c7b-b74b-2b0bac2e689b",
    "title": "Galactic Adventure",
    "description": "Journey Across the Stars.",
    "content": "n the vast expanse of space, where galaxies collide and stars are born, an epic adventure unfolds. From the bustling spaceports of bustling metropolises to the uncharted depths of the cosmos, our story takes us on a journey like no other. 2. Our adventure begins on the distant planet of Andromeda Prime, where a young pilot named Nova dreams of exploring the stars. With her trusty starship, the Stardust, by her side, she sets out on a quest to chart the unknown reaches of the galaxy. 3. Along the way, Nova encounters a colorful cast of characters, from swashbuckling space pirates to enigmatic alien scholars. Each encounter brings her one step closer to uncovering the secrets of the universe and her own mysterious past. 4. From the bustling markets of the galactic core to the serene tranquility of the outer rim, Nova's journey takes her to the farthest reaches of known space. Along the way, she discovers ancient ruins, hidden civilizations, and wonders beyond imagining. 5. But as Nova delves deeper into the mysteries of the cosmos, she also attracts the attention of powerful forces that seek to control her destiny. From ruthless corporate tycoons who see her as a threat to their profits to ancient cosmic entities who view her as a pawn in their cosmic game, she must navigate a web of intrigue and danger if she hopes to survive. 6. Yet with the help of her loyal crew and the power of friendship, Nova refuses to back down from the challenges that lie ahead. For she knows that the fate of the galaxy rests in her hands, and that only by embracing her true destiny can she hope to save the universe from destruction. 7. And so, with the stars as her guide and the wind at her back, Nova sets out to write her own legend among the stars. For in a galaxy filled with wonder and danger, the only limit is the strength of one's imagination.",
    "author": {
      "name": "Alex Turner",
      "email": "alex.turner@example.com"
    },
    "imageURL": "/assets/faces/3.svg",
    "backgroundimg": "/assets/4.jpg",
    "comments": []
  },
  {
    "token": "69f251f1-2a59-454a-b6ca-6788bfd50193",
    "title": "Metamorphosis: A Journey of Change",
    "description": "Exploring the Transformative Power of Life's Seasons.",
    "content": "Life is a river, flowing ever onward, winding its way through the landscape of our existence. From the gentle babbling brooks of youth to the rushing torrents of adulthood, each phase of life brings its own challenges and triumphs. 2. Our journey begins in the quiet stillness of dawn, as the first rays of sunlight pierce the darkness and illuminate the world with their golden glow. It is here, in the moments between waking and sleeping, that we find ourselves suspended in time, poised on the brink of change. 3. As the sun rises higher in the sky, we are drawn inexorably forward into the light of day. Along the way, we encounter obstacles and detours, moments of joy and sorrow, each shaping us in ways we cannot yet imagine. 4. And then, just when we think we have found our footing, life throws us a curveball, plunging us into the depths of uncertainty and doubt. It is in these moments of darkness that we discover our true strength, our inner resilience, as we navigate the twists and turns of fate. 5. But just as the river cannot be stopped in its course, so too must we continue to press forward, to embrace the changes that lie ahead. For in the ebb and flow of life, there is beauty to be found, in the turning of the seasons, the shifting of the tides. 6. And so, as the sun sets on another day, we find ourselves standing at the edge of tomorrow, ready to embark on a new journey, to face whatever challenges may come our way. For in the end, it is not the destination that matters, but the journey itself, and the lessons we learn along the way.",
    "author": {
      "name": "Samantha West",
      "email": "samantha.west@example.com"
    },
    "imageURL": "/assets/faces/4.svg",
    "backgroundimg": "/assets/5.jpg",
    "comments": []
  }
]
